chaosslack/__init__.py
chaosslack/control.py
chaosslack/notification.py
chaosslack/probes.py
chaostoolkit_slack-0.10.0.dist-info/LICENSE
chaostoolkit_slack-0.10.0.dist-info/METADATA
chaostoolkit_slack-0.10.0.dist-info/WHEEL
chaostoolkit_slack-0.10.0.dist-info/top_level.txt
chaostoolkit_slack-0.10.0.dist-info/RECORD
